LICENSE.txt
MANIFEST.in
setup.cfg
setup.py
hodl/__init__.py
hodl.egg-info/PKG-INFO
hodl.egg-info/SOURCES.txt
hodl.egg-info/dependency_links.txt
hodl.egg-info/entry_points.txt
hodl.egg-info/requires.txt
hodl.egg-info/top_level.txt
hodl/conf/config.ini