Metadata-Version: 1.1
Name: hodl
Version: 1.2.0
Summary: A  friendly, no-nonsense tool to instantaneously check cryptocurrency prices.
Home-page: https://github.com/netevert/hodl
Author: netevert
Author-email: netevert@protonmail.com
License: MIT
Keywords: cryptocurrencies exchange-rates coinbase command-line-tool hodl bitcoin bitcoin-api litecoin litecoin-price bitcoin-price ethereum bitcoin-cash
Platform: UNKNOWN
Classifier: Development Status :: 5 - Production/Stable
Classifier: Intended Audience :: Developers
Classifier: Intended Audience :: End Users/Desktop
Classifier: Intended Audience :: Information Technology
Classifier: Intended Audience :: Other Audience
Classifier: Intended Audience :: System Administrators
Classifier: Topic :: Office/Business :: Financial
Classifier: Topic :: Other/Nonlisted Topic
Classifier: Topic :: Terminals
Classifier: License :: OSI Approved :: MIT License
Classifier: Programming Language :: Python :: 2
Classifier: Programming Language :: Python :: 2.7
Classifier: Programming Language :: Python :: 3
Classifier: Programming Language :: Python :: 3.4
Classifier: Programming Language :: Python :: 3.5
Classifier: Programming Language :: Python :: 3.6
Classifier: Natural Language :: English
Classifier: Operating System :: Microsoft :: Windows
Classifier: Operating System :: MacOS
Classifier: Operating System :: POSIX :: Linux
